gcp_lolo/__init__.py
gcp_lolo/logger.py
gcp_lolo-2.0.2.dist-info/LICENSE
gcp_lolo-2.0.2.dist-info/METADATA
gcp_lolo-2.0.2.dist-info/WHEEL
gcp_lolo-2.0.2.dist-info/top_level.txt
gcp_lolo-2.0.2.dist-info/RECORD
