Metadata-Version: 2.2
Name: gcp-lolo
Version: 2.0.2
Summary: A Python package for storing application logs in GCP Cloud Logging.
Home-page: https://github.com/qurami/gcp-lolo
Author: Gianfranco Reppucci, ufirst
Author-email: gianfranco.reppucci@ufirst.com
License: MIT
Keywords: logging,GCP,Cloud Logging
Classifier: Programming Language :: Python :: 3
Classifier: Operating System :: OS Independent
Classifier: License :: OSI Approved :: MIT License
Classifier: Intended Audience :: Developers
Classifier: Topic :: Software Development :: Libraries :: Python Modules
Classifier: Topic :: System :: Logging
Classifier: Topic :: Utilities
License-File: LICENSE
Requires-Dist: google-api-core==2.24.2
Requires-Dist: google-auth==2.38.0
Requires-Dist: google-cloud-core>=2.0.0
Requires-Dist: google-cloud-logging>=3.0.0
Dynamic: author
Dynamic: author-email
Dynamic: classifier
Dynamic: description
Dynamic: description-content-type
Dynamic: home-page
Dynamic: keywords
Dynamic: license
Dynamic: requires-dist
Dynamic: summary
